LICENSE
bind_pool_executor/__init__.py
bind_pool_executor/main.py
bind_pool_executor/py.typed
bind_pool_executor-0.1.3.dist-info/LICENSE
bind_pool_executor-0.1.3.dist-info/WHEEL
bind_pool_executor-0.1.3.dist-info/METADATA
bind_pool_executor-0.1.3.dist-info/RECORD
