Metadata-Version: 2.1
Name: bind-pool-executor
Version: 0.1.3
Summary: 捆绑池处理，在一个工作执行完开始另一个工作的执行
Home-page: https://github.com/llango/bind-pool-executor
License: MIT
Author: Rontomai
Author-email: rontomai@gmail.com
Requires-Python: >=3.7,<4.0
Classifier: License :: OSI Approved :: MIT License
Classifier: Natural Language :: English
Classifier: Programming Language :: Python :: 3
Classifier: Programming Language :: Python :: 3.7
Classifier: Programming Language :: Python :: 3.8
Classifier: Programming Language :: Python :: 3.9
Requires-Dist: importlib_metadata (>=1.7.0,<2.0.0)
